opencrawl/__init__.py
opencrawl/open_crawl_api.py
opencrawl/opencrawl.py
opencrawl/website_crawler_db.py
opencrawl-0.1.7.dist-info/licenses/LICENSE
opencrawl-0.1.7.dist-info/METADATA
opencrawl-0.1.7.dist-info/WHEEL
opencrawl-0.1.7.dist-info/top_level.txt
opencrawl-0.1.7.dist-info/RECORD
